cor/__init__.py
cor/bibtex.py
cor/cli.py
cor/completions.py
cor/config.py
cor/crossref.py
cor/dependencies.py
cor/schema.py
cor/utils.py
cor/assets/backlog.md
cor/assets/note.md
cor/assets/project.md
cor/assets/ref.md
cor/assets/root.md
cor/assets/schema.yaml
cor/assets/task.md
cor/commands/__init__.py
cor/commands/dependencies.py
cor/commands/log.py
cor/commands/process.py
cor/commands/refactor.py
cor/commands/refs.py
cor/commands/status.py
cor/core/__init__.py
cor/core/archive.py
cor/core/files.py
cor/core/links.py
cor/core/notes.py
cor/core/refs.py
cor/hooks/pre-commit
cor/search/__init__.py
cor/search/completion.py
cor/search/fuzzy.py
cor/sync/__init__.py
cor/sync/runner.py
cortex_pkm-0.1.4.dist-info/licenses/LICENSE
cortex_pkm-0.1.4.dist-info/METADATA
cortex_pkm-0.1.4.dist-info/WHEEL
cortex_pkm-0.1.4.dist-info/entry_points.txt
cortex_pkm-0.1.4.dist-info/top_level.txt
cortex_pkm-0.1.4.dist-info/RECORD
