Metadata-Version: 2.4
Name: cortex-pkm
Version: 0.1.4
Summary: Plain text knowledge management
Author-email: lbugnon <lbugnon@sinc.unl.edu.ar>
License: MIT
Project-URL: Repository, https://github.com/lbugnon/cortex_pkm
Keywords: markdown,knowledge-management,notes,pkm,productivity
Classifier: Development Status :: 3 - Alpha
Classifier: Intended Audience :: Developers
Classifier: License :: OSI Approved :: MIT License
Classifier: Programming Language :: Python :: 3
Classifier: Programming Language :: Python :: 3.9
Classifier: Programming Language :: Python :: 3.10
Classifier: Programming Language :: Python :: 3.11
Classifier: Programming Language :: Python :: 3.12
Classifier: Topic :: Office/Business
Classifier: Topic :: Text Processing :: Markup :: Markdown
Requires-Python: >=3.11
License-File: LICENSE
Requires-Dist: click>=8.0
Requires-Dist: python-frontmatter>=1.0
Requires-Dist: rapidfuzz>=3.0
Requires-Dist: simple-term-menu>=1.6
Requires-Dist: habanero>=1.2
Requires-Dist: arxiv>=2.0.0
Requires-Dist: bibtexparser>=1.4
Requires-Dist: dateparser>=1.2
Provides-Extra: dev
Requires-Dist: pytest>=7.0; extra == "dev"
Dynamic: license-file
